taupy/__init__.py
taupy/analysis/__init__.py
taupy/analysis/agreement.py
taupy/analysis/clustering.py
taupy/analysis/diversity.py
taupy/analysis/doj.py
taupy/analysis/polarisation.py
taupy/analysis/voting.py
taupy/basic/__init__.py
taupy/basic/core.py
taupy/basic/positions.py
taupy/basic/utilities.py
taupy/generators/__init__.py
taupy/generators/maps.py
taupy/simulation/__init__.py
taupy/simulation/evaluation.py
taupy/simulation/simulation.py
taupy/simulation/strategies.py
taupy/simulation/update.py
taupy-0.5.0.dist-info/LICENSE
taupy-0.5.0.dist-info/METADATA
taupy-0.5.0.dist-info/WHEEL
taupy-0.5.0.dist-info/top_level.txt
taupy-0.5.0.dist-info/RECORD
