Metadata-Version: 2.1
Name: taupy
Version: 0.5.0
Summary: A Python package to study the theory of dialectical                  structures
Home-page: https://github.com/kopeckyf/taupy
Author: Felix Kopecky
License: UNKNOWN
Project-URL: Source, https://github.com/kopeckyf/taupy/
Project-URL: Bug Reports, https://github.com/kopeckyf/taupy/issues
Project-URL: Research group, https://debatelab.philosophie.kit.edu/
Keywords: Argumentation theory,Theory of dialectical structures,Argumentation framework,Agent-based debate model,ABM
Platform: UNKNOWN
Classifier: Development Status :: 5 - Production/Stable
Classifier: Intended Audience :: Science/Research
Classifier: Topic :: Sociology
Classifier: Topic :: Scientific/Engineering :: Artificial Intelligence
Classifier: License :: OSI Approved :: BSD License
Classifier: Programming Language :: Python :: 3
Classifier: Programming Language :: Python :: 3.9
Classifier: Programming Language :: Python :: 3.10
Classifier: Programming Language :: Python :: 3 :: Only
Requires-Python: >=3.9, <4
License-File: LICENSE
Requires-Dist: sympy (>=1.6.2)
Requires-Dist: dd (>=0.5.6)
Requires-Dist: numpy (>=1.19.4)
Requires-Dist: python-igraph (>=0.9.6)
Requires-Dist: scikit-learn (>=0.24.2)
Requires-Dist: pandas (>=1.2.2)
Requires-Dist: more-itertools (>=8.8.0)
Requires-Dist: z3-solver (>=4.8.14.0)
